MANIFEST.in
ez_setup.py
qldemo2json.py
qldemosummary.py
setup.py
huffman/huffman.c
huffman/pyhuffman.c
huffman/pyhuffman.h
huffman/q_shared.h
huffman/qcommon.h
ql_demo.egg-info/PKG-INFO
ql_demo.egg-info/SOURCES.txt
ql_demo.egg-info/dependency_links.txt
ql_demo.egg-info/top_level.txt
ql_demo.egg-info/zip-safe
qldemo/__init__.py
qldemo/constants.py
qldemo/data.py
qldemo/demo.py