Metadata-Version: 1.0
Name: ql-demo
Version: 0.4.12
Summary: Wrapper for Q3A Huffman Code Routines and QuakeLive Demo Utility Classes
Home-page: https://aphr.asia/gitweb/?p=qldemo-python.git;a=summary
Author: Shawn Nock
Author-email: nock@nocko.se
License: GPLv3
Keywords: quake quakelive demo dm_73 quakecon
Platform: UNKNOWN
